<?xml version="1.0" encoding="UTF-8"?>
<tv>
  <channel id="411952">
    <display-name>Jawa Pos TV Madiun (720p)</display-name>
  </channel>
  <channel id="411952">
    <display-name>Jawa Pos TV (720p)</display-name>
    <icon src="https://images.indihometv.com/images/channels/image_ch_jawapos.png"/>
  </channel>
  <channel id="171966">
    <display-name>Dhamma TV (720p) [Not 24/7]</display-name>
  </channel>
  <channel id="171924">
    <display-name>Bandung TV (360p)</display-name>
  </channel>
  <channel id="411915">
    <display-name>Biznet Adventure (1080p)</display-name>
  </channel>
  <channel id="171966">
    <display-name>Banjar TV (720p) [Not 24/7]</display-name>
  </channel>
  <channel id="171966">
    <display-name>Banyumas TV (720p) [Not 24/7]</display-name>
  </channel>
  <channel id="417396">
    <display-name>JTV (480p)</display-name>
    <icon src="https://images.indihometv.com/images/channels/image_ch_jtv.png"/>
  </channel>
  <channel id="171924">
    <display-name>Huma Betang TV (720p) [Not 24/7]</display-name>
  </channel>
  <channel id="411952">
    <display-name>Jawa Pos TV Bali (576p)</display-name>
  </channel>
  <channel id="411952">
    <display-name>Jawa Pos TV Magelang (720p)</display-name>
  </channel>
  <channel id="171966">
    <display-name>Inspira TV (720p) [Not 24/7]</display-name>
  </channel>
  <channel id="411952">
    <display-name>Jawa Pos TV Semarang (720p)</display-name>
  </channel>
  <channel id="411927">
    <display-name>CNBC Indonesia (720p)</display-name>
    <icon src="https://images.indihometv.com/images/channels/image_ch_cnbcindonesia.png"/>
  </channel>
  <channel id="411997">
    <display-name>Davika TV (480p)</display-name>
  </channel>
  <channel id="491643">
    <display-name>BRTV (720p)</display-name>
  </channel>
  <channel id="188223">
    <display-name>DAAI TV</display-name>
    <icon src="https://images.indihometv.com/images/channels/image_ch_daaitv.png"/>
  </channel>
  <channel id="411952">
    <display-name>Jawa Pos TV Jakarta (720p)</display-name>
  </channel>
  <channel id="171924">
    <display-name>Padang TV (720p) [Not 24/7]</display-name>
  </channel>
  <channel id="491701">
    <display-name>Kilisuci TV</display-name>
  </channel>
  <channel id="417396">
    <display-name>JTV Kediri</display-name>
  </channel>
  <channel id="172012">
    <display-name>Balikpapan TV (720p)</display-name>
  </channel>
  <channel id="411932">
    <display-name>Nusantara TV (1080p)</display-name>
    <icon src="https://images.indihometv.com/images/channels/image_ch_nusantaratv.png"/>
  </channel>
  <channel id="171966">
    <display-name>Radar Tasikmalaya TV (720p) [Not 24/7]</display-name>
  </channel>
  <channel id="171966">
    <display-name>Bungo TV (480p) [Not 24/7]</display-name>
  </channel>
  <channel id="171966">
    <display-name>RCTV (576p) [Not 24/7]</display-name>
  </channel>
  <channel id="171966">
    <display-name>Riau TV (1080p) [Not 24/7]</display-name>
  </channel>
  <channel id="171966">
    <display-name>STV (720p) [Not 24/7]</display-name>
  </channel>
  <channel id="171966">
    <display-name>MQTV (720p) [Not 24/7]</display-name>
  </channel>
  <channel id="411997">
    <display-name>Kawanua TV (720p)</display-name>
  </channel>
  <channel id="171966">
    <display-name>PKTV (480p) [Not 24/7]</display-name>
  </channel>
  <channel id="411997">
    <display-name>Elshinta TV</display-name>
  </channel>
  <channel id="171966">
    <display-name>SMTV (720p) [Not 24/7]</display-name>
  </channel>
  <channel id="171966">
    <display-name>Sampit TV (720p) [Not 24/7]</display-name>
  </channel>
  <channel id="412005">
    <display-name>U Channel (720p)</display-name>
    <icon src="https://images.indihometv.com/images/channels/image_ch_uchannel.png"/>
  </channel>
  <channel id="411915">
    <display-name>Biznet Kids (1080p)</display-name>
  </channel>
  <channel id="411938">
    <display-name>BeritaSatu English</display-name>
  </channel>
  <channel id="171991">
    <display-name>RBTV Jogja (1080p)</display-name>
  </channel>
  <channel id="171966">
    <display-name>Wesal TV (720p) [Not 24/7]</display-name>
  </channel>
  <channel id="171861">
    <display-name>Biznet Lifestyle (1080p)</display-name>
  </channel>
  <channel id="411950">
    <display-name>CNN Indonesia</display-name>
    <icon src="https://images.indihometv.com/images/channels/image_ch_cnnindonesia.png"/>
  </channel>
  <channel id="417399">
    <display-name>Trans7 (720p)</display-name>
    <icon src="https://images.indihometv.com/images/channels/image_ch_trans7.png"/>
  </channel>
  <channel id="411927">
    <display-name>CNBC Indonesia</display-name>
    <icon src="https://images.indihometv.com/images/channels/image_ch_cnbcindonesia.png"/>
  </channel>
  <channel id="171875">
    <display-name>MNC TV</display-name>
  </channel>
  <channel id="491701">
    <display-name>Music Information Channel (720p)</display-name>
  </channel>
  <channel id="11695">
    <display-name>Trans TV (720p)</display-name>
    <icon src="https://images.indihometv.com/images/channels/image_ch_transtv.png"/>
  </channel>
  <channel id="411932">
    <display-name>TV9 Nusantara (720p)</display-name>
  </channel>
  <channel id="11695">
    <display-name>Trans TV CDG</display-name>
  </channel>
  <channel id="417399">
    <display-name>Trans 7 CDG</display-name>
  </channel>
  <channel id="3809">
    <display-name>RTV ᴸᴼᵂ</display-name>
  </channel>
  <channel id="411970">
    <display-name>Rodja TV (720p)</display-name>
    <icon src="https://images.indihometv.com/images/channels/image_ch_rodjatv.png"/>
  </channel>
  <channel id="171875">
    <display-name>MNCTV World ᴸᴼᵂ</display-name>
  </channel>
  <channel id="171905">
    <display-name>JakTV ᴸᴼᵂ</display-name>
    <icon src="https://images.indihometv.com/images/channels/image_ch_jaktv.png"/>
  </channel>
  <channel id="171847">
    <display-name>Indosiar 2</display-name>
  </channel>
  <channel id="171847">
    <display-name>INDOSIAR</display-name>
    <icon src="https://images.indihometv.com/images/channels/image_ch_indosiar.png"/>
  </channel>
  <channel id="11695">
    <display-name>TransTV HD (TRANSCORP)</display-name>
    <icon src="https://images.indihometv.com/images/channels/image_ch_transtv.png"/>
  </channel>
  <channel id="411950">
    <display-name>CNN Indonesia (ChannelFeed)</display-name>
    <icon src="https://images.indihometv.com/images/channels/image_ch_cnnindonesia.png"/>
  </channel>
  <channel id="171933">
    <display-name>Indonesiana TV</display-name>
  </channel>
  <channel id="417399">
    <display-name>Trans7 HD (TRANSCORP)</display-name>
    <icon src="https://images.indihometv.com/images/channels/image_ch_trans7.png"/>
  </channel>
  <channel id="3958">
    <display-name>Astro Awani</display-name>
  </channel>
  <channel id="172012">
    <display-name>ANTV ᴸᴼᵂ</display-name>
    <icon src="https://images.indihometv.com/images/channels/image_ch_antv.png"/>
  </channel>
  <channel id="171931">
    <display-name>iNews ᴸᴼᵂ</display-name>
    <icon src="https://images.indihometv.com/images/channels/image_ch_inews.png"/>
  </channel>
  <channel id="417396">
    <display-name>JTV ᴸᴼᵂ</display-name>
    <icon src="https://images.indihometv.com/images/channels/image_ch_jtv.png"/>
  </channel>
  <channel id="171891">
    <display-name>Kompas TV ᴸᴼᵂ</display-name>
    <icon src="https://images.indihometv.com/images/channels/image_ch_kompastv.png"/>
  </channel>
  <channel id="171951">
    <display-name>Net TV</display-name>
  </channel>
  <channel id="411927">
    <display-name>CNBC Indonesia (ChannelFeed)</display-name>
    <icon src="https://images.indihometv.com/images/channels/image_ch_cnbcindonesia.png"/>
  </channel>
  <channel id="411997">
    <display-name>MAGNA TV (ChannelFeed)</display-name>
  </channel>
  <channel id="171991">
    <display-name>BTV ᴸᴼᵂ</display-name>
    <icon src="https://images.indihometv.com/images/channels/image_ch_btv.png"/>
  </channel>
  <channel id="171854">
    <display-name>SCTV</display-name>
    <icon src="https://images.indihometv.com/images/channels/image_ch_sctv.png"/>
  </channel>
  <channel id="171942">
    <display-name>Metro TV ᴸᴼᵂ</display-name>
    <icon src="https://images.indihometv.com/images/channels/image_ch_metrotv.png"/>
  </channel>
  <channel id="171991">
    <display-name>HBTV</display-name>
  </channel>
  <channel id="411974">
    <display-name>Bali TV ᴸᴼᵂ</display-name>
    <icon src="https://images.indihometv.com/images/channels/image_ch_balitv.png"/>
  </channel>
  <channel id="411961">
    <display-name>Hanacaraka TV ᴸᴼᵂ</display-name>
  </channel>
  <channel id="370131">
    <display-name>TV 6</display-name>
  </channel>
  <channel id="480059">
    <display-name>JR.</display-name>
  </channel>
  <channel id="411997">
    <display-name>Tea TV (720p)</display-name>
  </channel>
  <channel id="171870">
    <display-name>CGTN Documentary</display-name>
    <icon src="https://images.indihometv.com/images/channels/image_ch_cgtndocumentary.png"/>
  </channel>
  <channel id="172011">
    <display-name>TVRI Jakarta</display-name>
  </channel>
  <channel id="370132">
    <display-name>Berita RTM</display-name>
  </channel>
  <channel id="370133">
    <display-name>Sukan RTM</display-name>
  </channel>
  <channel id="171951">
    <display-name>Laos Planet TV (720p)</display-name>
  </channel>
  <channel id="171951">
    <display-name>NET TV HD</display-name>
  </channel>
  <channel id="479618">
    <display-name>AURA</display-name>
  </channel>
  <channel id="478719">
    <display-name>ROLL</display-name>
  </channel>
  <channel id="479449">
    <display-name>FITRAH</display-name>
  </channel>
  <channel id="478718">
    <display-name>LEAD</display-name>
  </channel>
  <channel id="479619">
    <display-name>APETITO</display-name>
  </channel>
  <channel id="478717">
    <display-name>SNAP</display-name>
  </channel>
  <channel id="411914">
    <display-name>Bein Sports 3 A 🟡</display-name>
  </channel>
  <channel id="171958">
    <display-name>IMTV</display-name>
  </channel>
  <channel id="412005">
    <display-name>BN Channel</display-name>
  </channel>
  <channel id="411956">
    <display-name>Bein Sports 1 A 🟡</display-name>
  </channel>
  <channel id="3683">
    <display-name>Champions TV 1</display-name>
  </channel>
  <channel id="411918">
    <display-name>Bein Sports 2 A 🟡</display-name>
  </channel>
  <channel id="417396">
    <display-name>PSJ TV</display-name>
  </channel>
  <channel id="171915">
    <display-name>Spotv A 🟡</display-name>
  </channel>
  <channel id="411956">
    <display-name>Bein Sports 1 🟥</display-name>
  </channel>
  <channel id="3711">
    <display-name>Champions TV 2</display-name>
  </channel>
  <channel id="411932">
    <display-name>Antara TV</display-name>
  </channel>
  <channel id="411949">
    <display-name>HORIZON SPORTS</display-name>
    <icon src="https://images.indihometv.com/images/channels/image_ch_horizonsport.png"/>
  </channel>
  <channel id="1072">
    <display-name>Champions TV 3</display-name>
  </channel>
  <channel id="370131">
    <display-name>Champions TV 6</display-name>
  </channel>
  <channel id="411997">
    <display-name>NBA TV A 🟡</display-name>
  </channel>
</tv>
